logtc/__init__.py
logtc/handler.py
logtc/logger.py
logtc/singleton.py
logtc/socket.py
logtc/utils.py
loggg-0.1.dist-info/METADATA
loggg-0.1.dist-info/WHEEL
loggg-0.1.dist-info/top_level.txt
loggg-0.1.dist-info/RECORD
