Metadata-Version: 2.1
Name: loggg
Version: 0.1
Summary: Log chains for webserver
Home-page: https://github.com/hoangtc125/logtc
Author: Cong Hoang Tran
Author-email: trconghoangg@gmail.com
Classifier: Programming Language :: Python :: 3
Classifier: License :: OSI Approved :: MIT License
Classifier: Operating System :: OS Independent
Requires-Python: >=3.6
Requires-Dist: requests
Requires-Dist: python-socketio
Requires-Dist: websocket-client
Requires-Dist: contextvars
